seamful/__init__.py
seamful/application/__init__.py
seamful/application/application.py
seamful/application/errors.py
seamful/application/graph_provider.py
seamful/application/graph_solver.py
seamful/application/registry.py
seamful/application/test_application.py
seamful/application/test_fixtures/test_application_TestApplicationCallingProviderMethods_test_provider_method_cannot_access_the_provider_instance.txt
seamful/application/test_fixtures/test_application_TestApplicationImplicitProviders_test_application_fails_on_closing_registration_if_any_implicit_provider_is_unused.txt
seamful/application/test_fixtures/test_application_TestApplicationImplicitProviders_test_can_install_private_provider_if_module_is_used.txt
seamful/application/test_fixtures/test_application_TestApplicationImplicitProviders_test_cant_install_private_provider_if_module_is_not_used.txt
seamful/application/test_fixtures/test_application_TestApplicationProvision_test_application_cant_provide_unknown_resource.txt
seamful/application/test_fixtures/test_application_TestApplicationProvision_test_application_refuses_to_provide_before_registrations_are_closed.txt
seamful/application/test_fixtures/test_application_TestApplicationProvision_test_refuses_to_provide_resource_not_defined_on_the_original_provider.txt
seamful/application/test_fixtures/test_application_TestApplicationRegistration_test_application_disallows_installing_a_module_twice.txt
seamful/application/test_fixtures/test_application_TestApplicationRegistration_test_application_install_provider_must_provide_for_module.txt
seamful/application/test_fixtures/test_application_TestApplicationRegistration_test_cannot_install_two_providers_for_the_same_module.txt
seamful/application/test_fixtures/test_application_TestApplicationRegistration_test_cant_install_module_after_ready.txt
seamful/application/test_fixtures/test_application_TestApplicationRegistration_test_cant_install_provider_after_ready.txt
seamful-0.2.0.dist-info/METADATA
seamful-0.2.0.dist-info/WHEEL
seamful-0.2.0.dist-info/RECORD
