Metadata-Version: 2.1
Name: seamful
Version: 0.2.0
Summary: Dependency management for python
Home-page: https://github.com/rdarder/seamful
License: MIT
Author: Rafael Darder
Author-email: darder@gmail.com
Requires-Python: >=3.7,<4.0
Classifier: License :: OSI Approved :: MIT License
Classifier: Programming Language :: Python :: 3
Classifier: Programming Language :: Python :: 3.7
Classifier: Programming Language :: Python :: 3.8
Classifier: Programming Language :: Python :: 3.9
Classifier: Programming Language :: Python :: 3.10
Classifier: Programming Language :: Python :: 3.11
Project-URL: Repository, https://github.com/rdarder/seamful
